bacpp/__init__.py
bacpp/cli.py
bacpp/examples/Citrobacter_freundii_ATCC_8090.fasta
bacpp/examples/Escherichia_coli.fna
bacpp/examples/Synechocystis_sp_PCC_6803.fasta
bacpp/models/MLG.json
bacpp/models/XGBoost.json
bacpp/models/kNNPC.json
bacpp-0.1.7.dist-info/LICENSE
bacpp-0.1.7.dist-info/METADATA
bacpp-0.1.7.dist-info/WHEEL
bacpp-0.1.7.dist-info/entry_points.txt
bacpp-0.1.7.dist-info/RECORD
