Metadata-Version: 2.3
Name: bacpp
Version: 0.1.7
Summary: Bacterial polyploidy predictor: A Machine Learning Tool for Bacterial Polyploidy Prediction from Genome Assemblies
License: MIT
Author: Zhenxiong Jiang
Author-email: jiangz1@ufl.edu
Requires-Python: >=3.9
Classifier: License :: OSI Approved :: MIT License
Classifier: Programming Language :: Python :: 3
Classifier: Programming Language :: Python :: 3.9
Classifier: Programming Language :: Python :: 3.10
Classifier: Programming Language :: Python :: 3.11
Classifier: Programming Language :: Python :: 3.12
Classifier: Programming Language :: Python :: 3.13
Requires-Dist: matplotlib (>=3.8,<4.0)
Requires-Dist: numpy (>=1.24,<2.0)
Requires-Dist: pandas (>=2.0,<3.0)
Requires-Dist: plotly (>=6.0,<7.0)
Requires-Dist: scikit-learn (>=1.5,<2.0)
Requires-Dist: xgboost (>=2.0,<3.0)
